{
  "main": {
    "id": "c652585a3c27fd79",
    "type": "split",
    "children": [
      {
        "id": "a5c1ad84bcfe3ff8",
        "type": "tabs",
        "children": [
          {
            "id": "16b9fec0a8affcaf",
            "type": "leaf",
            "state": {
              "type": "markdown",
              "state": {
                "file": "Exam Simulation/Section 2.md",
                "mode": "source",
                "source": false
              },
              "icon": "lucide-file",
              "title": "Section 2"
            }
          }
        ]
      }
    ],
    "direction": "vertical"
  },
  "left": {
    "id": "1357b7d3c6cc0f1d",
    "type": "split",
    "children": [
      {
        "id": "32f9637151e57698",
        "type": "tabs",
        "children": [
          {
            "id": "a4263eb0ef45c795",
            "type": "leaf",
            "state": {
              "type": "file-explorer",
              "state": {
                "sortOrder": "alphabetical",
                "autoReveal": false
              },
              "icon": "lucide-folder-closed",
              "title": "Files"
            }
          },
          {
            "id": "4006023fbe959311",
            "type": "leaf",
            "state": {
              "type": "search",
              "state": {
                "query": "",
                "matchingCase": false,
                "explainSearch": false,
                "collapseAll": false,
                "extraContext": false,
                "sortOrder": "alphabetical"
              },
              "icon": "lucide-search",
              "title": "Search"
            }
          },
          {
            "id": "b82e530aa099b454",
            "type": "leaf",
            "state": {
              "type": "bookmarks",
              "state": {},
              "icon": "lucide-bookmark",
              "title": "Bookmarks"
            }
          }
        ]
      }
    ],
    "direction": "horizontal",
    "width": 200
  },
  "right": {
    "id": "b3f71f33ce591960",
    "type": "split",
    "children": [
      {
        "id": "56979a6c4ca11ab2",
        "type": "tabs",
        "children": [
          {
            "id": "0b6fe10fa0a23248",
            "type": "leaf",
            "state": {
              "type": "backlink",
              "state": {
                "file": "متفرقات/Untitled.md",
                "collapseAll": false,
                "extraContext": false,
                "sortOrder": "alphabetical",
                "showSearch": false,
                "searchQuery": "",
                "backlinkCollapsed": false,
                "unlinkedCollapsed": true
              },
              "icon": "links-coming-in",
              "title": "Backlinks for Untitled"
            }
          },
          {
            "id": "a01d9a404bfb84e7",
            "type": "leaf",
            "state": {
              "type": "outgoing-link",
              "state": {
                "file": "متفرقات/Untitled.md",
                "linksCollapsed": false,
                "unlinkedCollapsed": true
              },
              "icon": "links-going-out",
              "title": "Outgoing links from Untitled"
            }
          },
          {
            "id": "8d83e2a71dbdb584",
            "type": "leaf",
            "state": {
              "type": "tag",
              "state": {
                "sortOrder": "frequency",
                "useHierarchy": true,
                "showSearch": false,
                "searchQuery": ""
              },
              "icon": "lucide-tags",
              "title": "Tags"
            }
          },
          {
            "id": "9b529688cc4ab471",
            "type": "leaf",
            "state": {
              "type": "all-properties",
              "state": {
                "sortOrder": "frequency",
                "showSearch": false,
                "searchQuery": ""
              },
              "icon": "lucide-archive",
              "title": "All properties"
            }
          },
          {
            "id": "99e4c975ce041180",
            "type": "leaf",
            "state": {
              "type": "outline",
              "state": {
                "file": "متفرقات/Untitled.md",
                "followCursor": false,
                "showSearch": false,
                "searchQuery": ""
              },
              "icon": "lucide-list",
              "title": "Outline of Untitled"
            }
          },
          {
            "id": "9572013764d1971d",
            "type": "leaf",
            "state": {
              "type": "git-view",
              "state": {},
              "icon": "git-pull-request",
              "title": "Source Control"
            }
          }
        ],
        "currentTab": 5
      }
    ],
    "direction": "horizontal",
    "width": 300,
    "collapsed": true
  },
  "left-ribbon": {
    "hiddenItems": {
      "switcher:Open quick switcher": false,
      "graph:Open graph view": false,
      "canvas:Create new canvas": false,
      "daily-notes:Open today's daily note": false,
      "templates:Insert template": false,
      "command-palette:Open command palette": false,
      "bases:Create new base": false,
      "obsidian-git:Open Git source control": false
    }
  },
  "active": "16b9fec0a8affcaf",
  "lastOpenFiles": [
    "Exam Simulation/Comparison Tables.md",
    "Exam Simulation/Section 2.md",
    "Exam Simulation/cheat sheet.md",
    "Exam Simulation/Total set 4.md",
    "Exam Simulation/Total set 5.md",
    "different explanations/حاجات متفرقة جات على بالي.md",
    "different explanations/Wrapers.md",
    "different explanations/var.md",
    "different explanations/Inner Classes.md",
    "different explanations/Functional interfaces.md",
    "different explanations/Untitled 1.md",
    "Exam Simulation/Section 1.md",
    "Exam Simulation/Total set 4 1.md",
    "Exam Simulation/Total set 3.md",
    "All lectures/Threading.md",
    "Exam Simulation/Total set 2.md",
    "All lectures/Java collections.md",
    "Exam Simulation/Total set 1.md",
    "All lectures/Stream API.md",
    "All lectures/The History and Evolution of Java.md",
    "All lectures/Wrapper Classes & inner classes.md",
    "All lectures/Exceptions.md",
    "All lectures/Generics and Lambda Expressions and Method Reference.md",
    "Exam Simulation/Section 3.md",
    "Exam Simulation/section 4.md",
    "Exam Simulation/section 5.md",
    "Exam Simulation",
    "All lectures",
    "different explanations"
  ]
}